asyncrandom.py
asyncrandom-0.0.1.dist-info/DESCRIPTION.rst
asyncrandom-0.0.1.dist-info/METADATA
asyncrandom-0.0.1.dist-info/RECORD
asyncrandom-0.0.1.dist-info/WHEEL
asyncrandom-0.0.1.dist-info/entry_points.txt
asyncrandom-0.0.1.dist-info/metadata.json
asyncrandom-0.0.1.dist-info/top_level.txt
