Metadata-Version: 2.0
Name: asyncrandom
Version: 0.0.1
Summary: Async random number generator.
Home-page: UNKNOWN
Author: Yavor Paunov
Author-email: contact@yavorpaunov.com
License: MIT
Platform: UNKNOWN
Requires-Dist: enum34
Requires-Dist: tornado (>=4.4)
